{
  "TagId": 0,
  "ThemeName": {
    "m_identifier": 169575957
  },
  "EmblemShaderName": {
    "m_identifier": -1
  },
  "AvailableConfigurations": [
    {
      "ConfigurationId": -1231529516,
      "ConfigurationPath": "Configuration/Emblems/Coatings/1000-000-98ad2fe2.json"
    }
  ],
  "CommonData": {
    "Id": "104-001-hcs-2023-clou-2b670ece",
    "HideUntilOwned": false,
    "Title": "Year 2 Cloud9 Launch",
    "Description": "#C9Win",
    "FeatureFlag": true,
    "ItemAvailability": "",
    "DateReleased": {
      "ISO8601Date": ""
    },
    "AltName": "104-001-hcs-2023-clou-2b670ece",
    "IconStringId": {
      "m_identifier": -1
    },
    "SpriteBitmap": 0,
    "SpriteFrameIndex": 0,
    "AltSpriteBitmap": 0,
    "AltSpriteFrameIndex": 0,
    "DisplayPath": {
      "Width": 2048,
      "Height": 2048,
      "Media": {
        "MediaUrl": {
          "AuthorityId": "",
          "Path": "progression/Inventory/Emblems/HCS_2023_CLOUD9_EMBLEM.png",
          "RetryPolicyId": "",
          "TopicName": "",
          "AcknowledgementTypeId": "NoAcknowledgement",
          "AuthenticationLifetimeExtensionSupported": false,
          "ClearanceAware": false
        },
        "MimeType": "",
        "Caption": "",
        "AlternateText": "",
        "FolderPath": "",
        "FileName": ""
      },
      "MimeType": "image/png",
      "FolderPath": "progression/Inventory/Emblems",
      "FileName": "HCS_2023_CLOUD9_EMBLEM.png"
    },
    "Quality": "Epic",
    "ManufacturerId": 0,
    "Type": "SpartanEmblem",
    "RewardTrack": "",
    "ParentPaths": [],
    "SortingMetadata": {
      "categoryWeight": 0,
      "subCategoryWeight": 0
    },
    "SeasonNumber": 3,
    "OriginalSeasonNumber": 3,
    "Season": {
      "status": "Ready",
      "value": "Season 3",
      "translations": {}
    }
  }
}