{
  "Title": {
    "status": "Ready",
    "value": "Ancient Flare",
    "translations": {
      "cs-CZ": "Starov\u011bk\u00e1 sv\u011btlice",
      "da-DK": "\u00c6ldgammelt signalblus",
      "de-DE": "Uralte Fackel",
      "el-GR": "\u0391\u03c1\u03c7\u03b1\u03af\u03b1 \u03b1\u03bd\u03b1\u03bb\u03b1\u03bc\u03c0\u03ae",
      "es-ES": "Bomba ancestral",
      "es-MX": "Bengala antigua",
      "fi-FI": "Muinainen soihtu",
      "fr-FR": "Fus\u00e9e ancienne",
      "hu-HU": "\u0150si f\u00e1klya",
      "it-IT": "Antico segnale",
      "ja-JP": "\u53e4\u306e\u70fd\u706b",
      "ko-KR": "\uace0\ub300\uc758 \ubd88\uaf43",
      "nb-NO": "Urgammelt bluss",
      "nl-NL": "Oud vuur",
      "pl-PL": "Staro\u017cytna raca",
      "pt-BR": "Sinalizador Antigo",
      "pt-PT": "Sinalizador Antigo",
      "ru-RU": "\u0414\u0440\u0435\u0432\u043d\u0438\u0439 \u0441\u0438\u0433\u043d\u0430\u043b\u044c\u043d\u044b\u0439 \u043e\u0433\u043e\u043d\u044c",
      "sv-SE": "Ur\u00e5ldrigt bloss",
      "tr-TR": "Kadim \u0130\u015faret Fi\u015fe\u011fi",
      "zh-CN": "\u53e4\u4ee3\u95ea\u5149\u5f39",
      "zh-TW": "\u53e4\u4ee3\u9707\u64bc\u5f48",
      "qps-ploc": "\u0386\u0149\u010b\u03b9\u0454\u0144\u0167 \u20a3\u0142\u0101\u0157\u00ea !!! ",
      "qps-ploca": "\u00c1\u207f\u0107\u0129\u0437\u03b7\u0165 \u20a3\u2113\u00e0\u0155\u00e8 !!! ",
      "qps-plocm": "\u00c3\u0438\u010d\u00ef\u0115\u043b\u0165 \u20a3\u2113\u0103\u0155\u00eb !!! "
    }
  },
  "Description": {
    "status": "Ready",
    "value": "Covenant raiders do not know honor, but they recognize wrath.",
    "translations": {
      "cs-CZ": "N\u00e1jezdn\u00edci Sme\u010dky nev\u011bd\u00ed, co je to \u010dest, ale dok\u00e1\u017eou rozpoznat hn\u011bv.",
      "da-DK": "Covenant-angribere kender ikke til \u00e6re, men de genkender vrede.",
      "de-DE": "Pl\u00fcnderer der Allianz kennen keine Ehre, daf\u00fcr aber Zorn.",
      "el-GR": "\u039f\u03b9 \u03a3\u03c5\u03bc\u03b2\u03b1\u03c4\u03b9\u03ba\u03bf\u03af \u03b5\u03c0\u03b9\u03b4\u03c1\u03bf\u03bc\u03b5\u03af\u03c2 \u03b4\u03b5\u03bd \u03c3\u03ba\u03b1\u03bc\u03c0\u03ac\u03b6\u03bf\u03c5\u03bd \u03b1\u03c0\u03cc \u03c4\u03b9\u03bc\u03ae, \u03b1\u03bb\u03bb\u03ac \u03b1\u03bd\u03b1\u03b3\u03bd\u03c9\u03c1\u03af\u03b6\u03bf\u03c5\u03bd \u03c4\u03b7\u03bd \u03bf\u03c1\u03b3\u03ae.",
      "es-ES": "Los asaltantes del Covenant no conocen el honor, pero s\u00ed la ira.",
      "es-MX": "Los asaltantes del Covenant no conocen el honor, pero reconocen la ira.",
      "fi-FI": "Covenantin ry\u00f6st\u00e4j\u00e4t eiv\u00e4t tunne kunniaa, mutta vihan ne kyll\u00e4 tunnistavat.",
      "fr-FR": "Les raiders covenants ne connaissent pas l\u2019honneur, mais ils savent reconna\u00eetre la fureur.",
      "hu-HU": "A Sz\u00f6vets\u00e9g fosztogat\u00f3i nem ismernek becs\u00fcletet, de felismerik a haragot.",
      "it-IT": "Gli incursori Covenant non conoscono l'onore, ma riconoscono l'ira.",
      "ja-JP": "\u30b3\u30f4\u30ca\u30f3\u30c8\u306e\u8972\u6483\u8005\u306b\u8a87\u308a\u306f\u306a\u3044\u304c\u3001\u6012\u308a\u306f\u3042\u308b\u3002",
      "ko-KR": "\ucf54\ubc84\ub10c\ud2b8 \uc2b5\uaca9\ub300\ub294 \uba85\uc608\ub97c \ubaa8\ub974\uc9c0\ub9cc, \ubd84\ub178\ub294 \uc555\ub2c8\ub2e4.",
      "nb-NO": "Covenants plyndrere kjenner ingen \u00e6re, men vrede kjenner de igjen.",
      "nl-NL": "Covenant-overvallers kennen geen eer, maar weten wel wat toorn is.",
      "pl-PL": "Naje\u017ad\u017acy Przymierza nie wiedz\u0105, czym jest honor, ale rozpoznaj\u0105 gniew.",
      "pt-BR": "Os invasores Covenant n\u00e3o sabem o significado da honra, mas conseguem reconhecer a ira.",
      "pt-PT": "Os invasores do Covenant n\u00e3o conhecem a honra, mas reconhecem a ira.",
      "ru-RU": "\u041d\u0430\u043b\u0451\u0442\u0447\u0438\u043a\u0438 \u041a\u043e\u0432\u0435\u043d\u0430\u043d\u0442\u0430 \u043d\u0435 \u0432\u0435\u0434\u0430\u044e\u0442 \u0447\u0435\u0441\u0442\u0438, \u043d\u043e \u0438\u043c \u0437\u043d\u0430\u043a\u043e\u043c\u0430 \u044f\u0440\u043e\u0441\u0442\u044c.",
      "sv-SE": "F\u00f6rbundets plundrare k\u00e4nner inte till heder, men de k\u00e4nner igen vrede.",
      "tr-TR": "Covenant ak\u0131nc\u0131lar\u0131 onur nedir bilmezler ama gazab\u0131 tan\u0131rlar.",
      "zh-CN": "\u661f\u76df\u7684\u88ad\u51fb\u8005\u5fc3\u4e2d\u6beb\u65e0\u8363\u8a89\u53ef\u8a00\uff0c\u4f46\u4ed6\u4eec\u77e5\u9053\u4ec0\u4e48\u662f\u6124\u6012\u3002",
      "zh-TW": "\u661f\u76df\u8972\u64ca\u8005\u4e0d\u77e5\u69ae\u8b7d\u70ba\u4f55\u7269\uff0c\u4f46\u537b\u7406\u89e3\u61a4\u6012\u3002",
      "qps-ploc": "\u00c7\u00f5\u03bd\u00e9\u03c0\u03b1\u014b\u0167 \u0159\u03ac\u012b\u03b4\u0437\u0157\u015b \u0111\u03b8 \u043b\u043e\u0163 \u043a\u0438\u01ff\u0448 \u0125\u00f6\u03b7\u014d\u0159, \u0432\u0171\u0167 \u03c4\u043d\u00e9\u1ef3 \u044f\u0115\u0441\u01ff\u011f\u03c0\u03af\u017e\u03ad \u0448\u0159\u0430\u03c4\u0452. !!! !!! !!! !!! !!! !!!",
      "qps-ploca": "\u0421\u0151\u03bd\u0451\u03b7\u01fb\u03c0\u0163 \u0157\u03b1\u03b9\u010f\u03ad\u0159\u0161 \u0111\u014f \u0144\u014d\u0165 \u045c\u043f\u03bf\u0175 \u043d\u00f4\u0146\u00f4\u0159, \u044a\u0446\u0442 \u0165\u043d\u0437\u1ef3 \u0157\u03b5\u0441\u03b8\u0123\u207f\u0456\u017e\u0117 \u1e83\u044f\u0434\u0442\u0452. !!! !!! !!! !!! !!! !!!",
      "qps-plocm": "\u20ac\u03b8\u03bd\u0117\u0149\u01fb\u03b7\u0167 \u0155\u0434\u00ee\u0111\u0113\u0157\u0161 \u00f0\u00f8 \u014b\u00f8\u0165 \u045c\u207f\u00f3\u1e81 \u045b\u00f8\u03ae\u03cc\u0155, \u044c\u0171\u0442 \u03c4\u0452\u0435\u00ff \u044f\u00e9\u00a2\u03cc\u0121\u03ae\u0129\u017c\u00eb \u1e81\u0453\u00e4\u03c4\u045b. !!! !!! !!! !!! !!! !!!"
    }
  },
  "Quality": "Epic",
  "WidthHint": 2,
  "HeightHint": 1,
  "FlairText": {
    "status": "Ready",
    "value": "Daily",
    "translations": {
      "cs-CZ": "Denn\u011b",
      "da-DK": "Daglig",
      "de-DE": "T\u00e4glich",
      "el-GR": "K\u03b1\u03b8\u03b7\u03bc\u03b5\u03c1\u03b9\u03bd\u03ac",
      "es-ES": "Diario",
      "es-MX": "Diario",
      "fi-FI": "P\u00e4ivitt\u00e4inen",
      "fr-FR": "Par jour",
      "hu-HU": "Napi",
      "it-IT": "Giornaliero",
      "ja-JP": "\u30c7\u30a4\u30ea\u30fc",
      "ko-KR": "\uc77c\uc77c",
      "nb-NO": "Daglig",
      "nl-NL": "Dagelijks",
      "pl-PL": "Codzienne",
      "pt-BR": "Di\u00e1rio",
      "pt-PT": "Diariamente",
      "ru-RU": "\u0415\u0436\u0435\u0434\u043d\u0435\u0432\u043d\u043e",
      "sv-SE": "Dagliga",
      "tr-TR": "G\u00fcnl\u00fck",
      "zh-CN": "\u6bcf\u65e5",
      "zh-TW": "\u6bcf\u65e5",
      "qps-ploc": "\u010e\u00e4\u03b9\u013a\u00ff !",
      "qps-ploca": "\u00d0\u00e5\u03af\u0140\u00fd !",
      "qps-plocm": "\u0110\u03ac\u00ec\u013a\u00ff !"
    }
  },
  "FlairIconPath": "progression/StoreContent/FlairIcons/RitualIconFlair.png",
  "FlairBackgroundPath": "progression/StoreContent/FlairBackgrounds/RitualBackgroundFlair.png",
  "ObjectImagePath": "progression/StoreContent/Offerings/S1_Ancient_Flare.png",
  "HasFlair": true
}