{
  "Title": {
    "status": "Ready",
    "value": "Strong Iris - BR75 Battle Rifle",
    "translations": {
      "cs-CZ": "Siln\u00e1 duhovka - BR75 bojov\u00e1 pu\u0161ka",
      "da-DK": "Strong Iris - BR75-kampriffel",
      "de-DE": "Starke Iris \u2013 BR75 Kampfgewehr",
      "el-GR": "\u0399\u03c3\u03c7\u03c5\u03c1\u03ae \u038a\u03c1\u03b9\u03b4\u03b1 - \u03a4\u03bf\u03c5\u03c6\u03ad\u03ba\u03b9 \u039c\u03ac\u03c7\u03b7\u03c2 BR75",
      "es-ES": "Iris intenso: fusil de combate BR75",
      "es-MX": "Iris fuerte - Rifle de batalla BR75",
      "fi-FI": "Vahva Iris - BR75-taistelukiv\u00e4\u00e4ri",
      "fr-FR": "Iris robuste - Fusil de combat BR75",
      "hu-HU": "Er\u0151s \u00edrisz \u2013 BR75 rohampuska",
      "it-IT": "Iris forte: fucile da battaglia BR75",
      "ja-JP": "\u30b9\u30c8\u30ed\u30f3\u30b0 \u30a2\u30a4\u30ea\u30b9 - BR75 \u30d0\u30c8\u30eb\u30e9\u30a4\u30d5\u30eb",
      "ko-KR": "\uc9c4\ud55c \ubd93\uaf43\uc0c9 - BR75 \ubc30\ud2c0 \ub77c\uc774\ud50c",
      "nb-NO": "Sterk iris - BR75-kamprifle",
      "nl-NL": "Sterke iris - BR75-battlegeweer",
      "pl-PL": "Wyrazista t\u0119cz\u00f3wka \u2013 karabin bojowy BR75",
      "pt-BR": "\u00cdris Forte - Rifle de Batalha BR75",
      "pt-PT": "\u00cdris Forte - Espingarda de Batalha BR75",
      "ru-RU": "\u0421\u0438\u043b\u044c\u043d\u0430\u044f \u0440\u0430\u0434\u0443\u0433\u0430 \u2014 \u0431\u043e\u0435\u0432\u0430\u044f \u0432\u0438\u043d\u0442\u043e\u0432\u043a\u0430 BR75",
      "sv-SE": "Stark iris \u2013 BR75-stridsgev\u00e4r",
      "tr-TR": "G\u00fc\u00e7l\u00fc \u0130ris - BR75 Sava\u015f T\u00fcfe\u011fi",
      "zh-CN": "\u9e22\u5c3e\u7d2b - BR75 \u6218\u6597\u6b65\u67aa",
      "zh-TW": "\u9cf6\u5c3e\u7d2b - BR75 \u653b\u64ca\u6b65\u69cd",
      "qps-ploc": "\u015c\u03c4\u0453\u00f8\u0439\u0123 \u03aa\u0159\u0457\u0161 - \u042c\u042f75 \u0412\u0101\u0442\u0167\u013e\u0451 \u0413\u00ed\u0192\u013c\u0117 !!! !!! !!!",
      "qps-ploca": "\u015a\u0442\u044f\u0151\u014b\u011d \u0128\u0157\u03af\u015f - \u0411\u049075 \u03b2\u0103\u0167\u0163\u0140\u03b5 \u0156\u0129\u0192\u2113\u00e8 !!! !!! !!!",
      "qps-plocm": "\u0160\u0442\u0433\u03b8\u03b7\u0121 \u0406\u0159\u03ca\u015b - \u03b2\u049075 \u0392\u00e1\u03c4\u0442\u013a\u00ea \u0490\u0456\u0192\u013c\u0113 !!! !!! !!!"
    }
  },
  "Description": {
    "status": "Ready",
    "value": "Unshakeable. Unbreakable.",
    "translations": {
      "cs-CZ": "Neochv\u011bjn\u00e9. Nezni\u010diteln\u00e9.",
      "da-DK": "Wheat Cedar",
      "de-DE": "Unersch\u00fctterlich. Unzerst\u00f6rbar.",
      "el-GR": "\u0391\u03ba\u03bb\u03cc\u03bd\u03b7\u03c4\u03bf\u03c2. \u0386\u03b8\u03c1\u03b1\u03c5\u03c3\u03c4\u03bf\u03c2.",
      "es-ES": "Tenaz e inquebrantable.",
      "es-MX": "Imperturbable. Indestructible.",
      "fi-FI": "Horjumaton. Murtumaton.",
      "fr-FR": "In\u00e9branlable. Incassable.",
      "hu-HU": "Megingathatatlan. Megt\u00f6rhetetlen.",
      "it-IT": "Incrollabile. Indistruttibile.",
      "ja-JP": "\u63fa\u308b\u304e\u306a\u3057\u3002\u6f70\u3048\u308b\u3053\u3068\u306a\u3057\u3002",
      "ko-KR": "\ud754\ub4e4\ub9ac\uc9c0\ub3c4 \uc54a\uace0, \ubb34\ub108\uc9c0\uc9c0\ub3c4 \uc54a\uc2b5\ub2c8\ub2e4.",
      "nb-NO": "Urokkelig. Uknuselig.",
      "nl-NL": "Onverstoorbaar. Onbreekbaar.",
      "pl-PL": "Niez\u0142omny i niezniszczalny.",
      "pt-BR": "Inabal\u00e1vel. Inquebr\u00e1vel.",
      "pt-PT": "Inabal\u00e1vel. Inquebr\u00e1vel.",
      "ru-RU": "\u041d\u0435\u043f\u043e\u043a\u043e\u043b\u0435\u0431\u0438\u043c\u043e\u0441\u0442\u044c. \u041d\u0435\u0441\u043e\u043a\u0440\u0443\u0448\u0438\u043c\u043e\u0441\u0442\u044c.",
      "sv-SE": "Orubblig. Obeveklig.",
      "tr-TR": "Sars\u0131lmaz. Y\u0131k\u0131lmaz.",
      "zh-CN": "\u65e0\u6cd5\u52a8\u6447\u3001\u7262\u4e0d\u53ef\u7834\u3002",
      "zh-TW": "\u7121\u6cd5\u52d5\u6416\u3001\u7262\u4e0d\u53ef\u7834\u3002",
      "qps-ploc": "\u0170\u0148\u015b\u043d\u0101\u03ba\u212e\u0434\u044a\u013a\u00e9. \u00da\u014b\u044a\u0453\u0451\u0434\u03ba\u00aa\u0432\u2113\u0119. !!! !!! !",
      "qps-ploca": "\u00db\u0439\u015f\u045b\u03b1\u03ba\u00e9\u0105\u044a\u0142\u00eb. \u016a\u0146\u044a\u0159\u044d\u03ac\u043a\u00e1\u0432\u0142\u03ad. !!! !!! !",
      "qps-plocm": "\u00da\u0148\u015f\u0127\u00e0\u0137\u0454\u00e3\u044a\u0140\u212e. \u016a\u03c0\u044c\u0157\u00e9\u00e1\u0138\u00e1\u0432\u013e\u0437. !!! !!! !"
    }
  },
  "Quality": "Rare",
  "WidthHint": 2,
  "HeightHint": 1,
  "FlairText": {
    "status": "Test",
    "value": "DAILY",
    "translations": {
      "qps-ploc": "\u00d0\u0394\u0407\u0141\u00a5 !",
      "qps-ploca": "\u0110\u0391\u00cd\u00a3\u0176 !",
      "qps-plocm": "\u00d0\u0391\u012a\u013b\u0176 !"
    }
  },
  "FlairIconPath": "progression/StoreContent/FlairIcons/RitualIconFlair.png",
  "FlairBackgroundPath": "progression/StoreContent/FlairBackgrounds/RitualBackgroundFlair.png",
  "ObjectImagePath": "progression/StoreContent/Offerings/2023_S3_StrongIris-BR75BattleRifle_Bundle_2x1.png",
  "HasGleam": null,
  "IsOnSale": null,
  "SalePercentage": null,
  "IsEventItem": null,
  "IsNew": false,
  "FlairBackgroundColorOverrideRGB": null,
  "FlairTextColorOverrideRGB": null,
  "TitleColorOverrideRGB": null,
  "PriceColorOverrideRGB": null,
  "PriceShadowColorOverrideRGB": null,
  "HasFlair": true,
  "FlairIcon": "progression/StoreContent/FlairIcons/RitualIconFlair.png",
  "FlairBackground": "progression/StoreContent/FlairBackgrounds/RitualBackgroundFlair.png",
  "StoreTileType": "StoreOffer"
}